{"web_url": "http://www.nytimes.com/2016/01/11/opinion/sharing-the-profits-from-cell-research.html", "snippet": "Readers say the issue of profits should be transparent for donors of cells and tissue.", "multimedia": [], "byline": [], "lead_paragraph": "Readers say the issue of profits should be transparent for donors of cells and tissue.", "abstract": null, "keywords": [{"is_major": "N", "rank": "1", "name": "subject", "value": "Research"}, {"is_major": "N", "rank": "2", "name": "subject", "value": "Privacy"}, {"is_major": "N", "rank": "3", "name": "subject", "value": "DNA (Deoxyribonucleic Acid)"}, {"is_major": "N", "rank": "4", "name": "subject", "value": "Medicine and Health"}, {"is_major": "N", "rank": "5", "name": "subject", "value": "Genetics and Heredity"}], "section_name": "Opinion", "blog": [], "_id": "569365f638f0d801cf86fb33", "slideshow_credits": null, "pub_date": "2016-01-11T00:00:00Z", "type_of_material": "Letter", "print_page": "22", "subsection_name": null, "source": "The New York Times", "word_count": "597", "document_type": "article", "news_desk": "Letters", "headline": {"kicker": "Letters", "content_kicker": "Letters", "main": "Sharing the Profits From Cell Research", "print_headline": "Sharing the Profits From Cell Research"}}