{"web_url": "http://www.nytimes.com/2016/01/03/fashion/weddings/francesca-oliva-christopher-carozza.html", "snippet": "The couple met in April 2012 while working together at a Manhattan law firm.", "multimedia": [{"height": 126, "subtype": "wide", "url": "images/2016/01/03/fashion/weddings/03OLIVAjpg/03OLIVAjpg-thumbWide-v2.jpg", "width": 190, "type": "image", "legacy": {"wideheight": "126", "wide": "images/2016/01/03/fashion/weddings/03OLIVAjpg/03OLIVAjpg-thumbWide-v2.jpg", "widewidth": "190"}}, {"height": 354, "subtype": "xlarge", "url": "images/2016/01/03/fashion/weddings/03OLIVAjpg/03OLIVAjpg-articleLarge-v2.jpg", "width": 600, "type": "image", "legacy": {"xlarge": "images/2016/01/03/fashion/weddings/03OLIVAjpg/03OLIVAjpg-articleLarge-v2.jpg", "xlargeheight": "354", "xlargewidth": "600"}}, {"height": 75, "subtype": "thumbnail", "url": "images/2016/01/03/fashion/weddings/03OLIVAjpg/03OLIVAjpg-thumbStandard-v2.jpg", "width": 75, "type": "image", "legacy": {"thumbnail": "images/2016/01/03/fashion/weddings/03OLIVAjpg/03OLIVAjpg-thumbStandard-v2.jpg", "thumbnailwidth": "75", "thumbnailheight": "75"}}], "byline": [], "lead_paragraph": "The couple met in April 2012 while working together at a Manhattan law firm.", "abstract": null, "keywords": [{"is_major": "N", "rank": "1", "name": "subject", "value": "Weddings and Engagements"}], "section_name": "Fashion & Style", "blog": [], "_id": "5688ae5a38f0d81904703962", "slideshow_credits": null, "pub_date": "2016-01-03T00:00:00Z", "type_of_material": "News", "print_page": "9", "subsection_name": "Weddings", "source": "The New York Times", "word_count": "220", "document_type": "article", "news_desk": "Society", "headline": {"print_headline": "Francesca Oliva,  Christopher Carozza", "main": "Francesca Oliva, Christopher Carozza"}}