{"web_url": "http://takingnote.blogs.nytimes.com/2016/01/13/what-would-you-ask-hillary-clinton/", "snippet": "Mrs. Clinton will answer a reader question when she visits the editorial board on Thursday.", "multimedia": [{"height": 126, "subtype": "wide", "url": "images/2016/01/13/opinion/13editorsWEB/13editorsWEB-thumbWide.jpg", "width": 190, "type": "image", "legacy": {"wideheight": "126", "wide": "images/2016/01/13/opinion/13editorsWEB/13editorsWEB-thumbWide.jpg", "widewidth": "190"}}, {"height": 400, "subtype": "xlarge", "url": "images/2016/01/13/opinion/13editorsWEB/13editorsWEB-articleLarge.jpg", "width": 600, "type": "image", "legacy": {"xlarge": "images/2016/01/13/opinion/13editorsWEB/13editorsWEB-articleLarge.jpg", "xlargeheight": "400", "xlargewidth": "600"}}, {"height": 75, "subtype": "thumbnail", "url": "images/2016/01/13/opinion/13editorsWEB/13editorsWEB-thumbStandard.jpg", "width": 75, "type": "image", "legacy": {"thumbnail": "images/2016/01/13/opinion/13editorsWEB/13editorsWEB-thumbStandard.jpg", "thumbnailwidth": "75", "thumbnailheight": "75"}}], "byline": {"organization": "THE EDITORS", "original": "By THE EDITORS", "person": []}, "lead_paragraph": null, "abstract": "Mrs. Clinton will answer a reader question when she visits the editorial board on Thursday.", "keywords": [{"value": "Clinton, Hillary Rodham", "rank": "1", "name": "persons"}, {"value": "Democratic Party", "rank": "1", "name": "organizations"}, {"value": "State Department", "rank": "2", "name": "organizations"}, {"value": "Presidential Election of 2016", "rank": "1", "name": "subject"}, {"value": "United States Politics and Government", "rank": "2", "name": "subject"}], "section_name": "Opinion", "blog": [], "_id": "5696834a38f0d865e6c347fe", "slideshow_credits": null, "pub_date": "2016-01-13T12:01:42Z", "type_of_material": "Blog", "print_page": null, "subsection_name": null, "source": "The New York Times", "word_count": "91", "document_type": "blogpost", "news_desk": "OpEd", "headline": {"kicker": "Taking Note", "main": "What Would You Ask Hillary Clinton?"}}