{"lead_paragraph": "Vladislav Namestnikov\u2019s third goal, 2 minutes 11 seconds into overtime, lifted Tampa Bay over Pittsburgh, 5-4, for its fourth straight win.", "pub_date": "2016-01-16T00:00:00Z", "slideshow_credits": null, "byline": {"contributor": "", "organization": "THE ASSOCIATED PRESS", "person": [], "original": "By THE ASSOCIATED PRESS"}, "document_type": "article", "section_name": "Sports", "snippet": "Vladislav Namestnikov\u2019s third goal, 2 minutes 11 seconds into overtime, lifted Tampa Bay over Pittsburgh, 5-4, for its fourth straight win.", "multimedia": [], "blog": [], "type_of_material": "News", "headline": {"main": "Lightning Top Penguins as Overtime Goal Finishes Hat Trick", "print_headline": "Lightning Top Penguins as Overtime Goal Finishes Hat Trick", "content_kicker": "N.H.L. Roundup", "kicker": "N.H.L. Roundup"}, "keywords": [{"rank": "1", "name": "subject", "is_major": "Y", "value": "Hockey, Ice"}, {"rank": "2", "name": "organizations", "is_major": "Y", "value": "Pittsburgh Penguins"}, {"rank": "3", "name": "organizations", "is_major": "Y", "value": "Tampa Bay Lightning"}], "web_url": "http://www.nytimes.com/2016/01/16/sports/hockey/nhl-roundup.html", "print_page": "7", "source": "The New York Times", "news_desk": "Sports", "abstract": "NHL Roundup; Tampa Bay Lightning defeats Pittsburgh Penguins, 5-4; other hockey scores noted.", "word_count": "326", "_id": "5699cda538f0d86a572ec182", "subsection_name": "Hockey"}