{"web_url": "http://www.nytimes.com/2016/01/13/movies/directors-guild-nominates-revenant-spotlight-and-big-short.html", "snippet": "\u201cMad Max\u201d and \u201cMartian\u201d also make the Directors Guild list, but \u201cCarol\u201d is shut out.", "multimedia": [{"height": 126, "subtype": "wide", "url": "images/2016/01/13/arts/13artsbeat-inarritu/13artsbeat-inarritu-thumbWide.jpg", "width": 190, "type": "image", "legacy": {"wideheight": "126", "wide": "images/2016/01/13/arts/13artsbeat-inarritu/13artsbeat-inarritu-thumbWide.jpg", "widewidth": "190"}}, {"height": 435, "subtype": "xlarge", "url": "images/2016/01/13/arts/13artsbeat-inarritu/13artsbeat-inarritu-articleLarge.jpg", "width": 600, "type": "image", "legacy": {"xlarge": "images/2016/01/13/arts/13artsbeat-inarritu/13artsbeat-inarritu-articleLarge.jpg", "xlargeheight": "435", "xlargewidth": "600"}}, {"height": 75, "subtype": "thumbnail", "url": "images/2016/01/13/arts/13artsbeat-inarritu/13artsbeat-inarritu-thumbStandard.jpg", "width": 75, "type": "image", "legacy": {"thumbnail": "images/2016/01/13/arts/13artsbeat-inarritu/13artsbeat-inarritu-thumbStandard.jpg", "thumbnailwidth": "75", "thumbnailheight": "75"}}], "byline": null, "lead_paragraph": "\u201cMad Max\u201d and \u201cMartian\u201d also make the Directors Guild list, but \u201cCarol\u201d is shut out.", "abstract": "Directors Guild of America announces nominees for its feature film awards; partial list of nominees noted. ", "keywords": [{"is_major": "Y", "rank": "1", "name": "organizations", "value": "Directors Guild of America"}, {"is_major": "Y", "rank": "2", "name": "subject", "value": "Movies"}, {"is_major": "N", "rank": "3", "name": "persons", "value": "Inarritu, Alejandro G"}, {"is_major": "N", "rank": "4", "name": "persons", "value": "McCarthy, Tom (1966- )"}, {"is_major": "N", "rank": "5", "name": "persons", "value": "McKay, Adam"}, {"is_major": "N", "rank": "6", "name": "persons", "value": "Miller, George (1945- )"}, {"is_major": "N", "rank": "7", "name": "persons", "value": "Scott, Ridley"}, {"is_major": "N", "rank": "1", "name": "glocations", "value": "Randalls Island (Manhattan, NY)"}, {"is_major": "Y", "rank": "2", "name": "organizations", "value": "Goldenvoice"}, {"is_major": "Y", "rank": "3", "name": "subject", "value": "Festivals"}, {"is_major": "Y", "rank": "4", "name": "subject", "value": "Music"}, {"is_major": "N", "rank": "5", "name": "organizations", "value": "Anschutz Entertainment Group (AEG) Live"}, {"is_major": "Y", "rank": "6", "name": "subject", "value": "Governors Ball Music Festival"}], "section_name": "Movies", "blog": [], "_id": "569546ee38f0d83e7cfe02dd", "slideshow_credits": null, "pub_date": "2016-01-13T00:00:00Z", "type_of_material": "News", "print_page": "3", "subsection_name": null, "source": "The New York Times", "word_count": "220", "document_type": "article", "news_desk": "Culture", "headline": {"content_kicker": "The Carpetbagger", "main": "Directors Guild Nominates \u2018Revenant,\u2019 \u2018Spotlight\u2019 and \u2018Big Short\u2019", "print_headline": "Directors Guild Releases Its Film Nominees"}}