{"lead_paragraph": "The Standard & Poor\u2019s 500-stock index is down 10 percent from its November peak. Oil erased early gains after a disappointing report on supply.", "pub_date": "2016-01-14T00:00:00Z", "slideshow_credits": null, "byline": {"organization": "THE ASSOCIATED PRESS", "person": [], "original": "By THE ASSOCIATED PRESS"}, "document_type": "article", "section_name": "Business Day", "snippet": "The Standard & Poor\u2019s 500-stock index is down 10 percent from its November peak. Oil erased early gains after a disappointing report on supply.", "multimedia": [], "blog": [], "type_of_material": "News", "headline": {"main": "Markets Close Sharply Lower as Oil Prices Waver"}, "keywords": [{"rank": "1", "name": "subject", "is_major": "N", "value": "Stocks and Bonds"}, {"rank": "2", "name": "subject", "is_major": "N", "value": "Nasdaq Composite Index"}, {"rank": "3", "name": "subject", "is_major": "N", "value": "Standard & Poor's 500-Stock Index"}, {"rank": "4", "name": "subject", "is_major": "N", "value": "Dow Jones Stock Average"}], "web_url": "http://www.nytimes.com/2016/01/14/business/daily-stock-market-activity.html", "print_page": null, "source": "The New York Times", "news_desk": "Business", "abstract": null, "word_count": "610", "_id": "5696651a38f0d83e7cfe0646", "subsection_name": null}