{"web_url": "http://www.nytimes.com/2016/01/23/opinion/the-fading-two-state-solution.html", "snippet": "The American ambassador was right to prod Israel about the direction it is heading.", "multimedia": [{"height": 126, "subtype": "wide", "url": "images/2016/01/23/opinion/23sat1/23sat1-thumbWide.jpg", "width": 190, "type": "image", "legacy": {"wideheight": "126", "wide": "images/2016/01/23/opinion/23sat1/23sat1-thumbWide.jpg", "widewidth": "190"}}, {"height": 744, "subtype": "xlarge", "url": "images/2016/01/23/opinion/23sat1/23sat1-articleLarge.jpg", "width": 600, "type": "image", "legacy": {"xlarge": "images/2016/01/23/opinion/23sat1/23sat1-articleLarge.jpg", "xlargeheight": "744", "xlargewidth": "600"}}, {"height": 75, "subtype": "thumbnail", "url": "images/2016/01/23/opinion/23sat1/23sat1-thumbStandard.jpg", "width": 75, "type": "image", "legacy": {"thumbnail": "images/2016/01/23/opinion/23sat1/23sat1-thumbStandard.jpg", "thumbnailwidth": "75", "thumbnailheight": "75"}}], "byline": {"organization": "THE EDITORIAL BOARD", "original": "By THE EDITORIAL BOARD", "person": []}, "lead_paragraph": "The American ambassador was right to prod Israel about the direction it is heading.", "abstract": "Editorial points to unfair criticism made by Israeli Prime Min Benjamin Netanyahu and his right-wing government about speech given by Daniel Shapiro, American ambassador in Tel Aviv; says fiery backlash is further evidence of Israeli government's move away from seeking two-state solution, for which, lamentably, it may be too late. ", "keywords": [{"is_major": "Y", "rank": "1", "name": "subject", "value": "Editorials"}, {"is_major": "Y", "rank": "2", "name": "subject", "value": "Palestinians"}, {"is_major": "Y", "rank": "3", "name": "persons", "value": "Netanyahu, Benjamin"}, {"is_major": "Y", "rank": "4", "name": "persons", "value": "Shapiro, Daniel B"}, {"is_major": "N", "rank": "5", "name": "persons", "value": "Obama, Barack"}, {"is_major": "N", "rank": "6", "name": "subject", "value": "United States International Relations"}, {"is_major": "Y", "rank": "7", "name": "glocations", "value": "Israel"}], "section_name": "Opinion", "blog": [], "_id": "56a2e4a538f0d85aa1bb1998", "slideshow_credits": null, "pub_date": "2016-01-23T00:00:00Z", "type_of_material": "Editorial", "print_page": "18", "subsection_name": null, "source": "The New York Times", "word_count": "672", "document_type": "article", "news_desk": "Editorial", "headline": {"kicker": "Editorial", "content_kicker": "Editorial", "main": "The Fading Two-State Solution", "print_headline": "The Fading Two-State Solution"}}