{"web_url": "http://www.nytimes.com/2016/01/05/opinion/a-caregiving-credit-for-social-security-benefits.html", "snippet": "A reader praises a suggestion by Eduardo Porter to lessen the penalty for those who leave jobs to care for loved ones.", "multimedia": [], "byline": [], "lead_paragraph": "A reader praises a suggestion by Eduardo Porter to lessen the penalty for those who leave jobs to care for loved ones.", "abstract": null, "keywords": [{"is_major": "N", "rank": "1", "name": "subject", "value": "Elderly"}, {"is_major": "N", "rank": "2", "name": "subject", "value": "Social Security (US)"}, {"is_major": "N", "rank": "3", "name": "subject", "value": "Elder Care"}], "section_name": "Opinion", "blog": [], "_id": "568b7cf238f0d85e74bd0c11", "slideshow_credits": null, "pub_date": "2016-01-05T00:00:00Z", "type_of_material": "Letter", "print_page": "22", "subsection_name": null, "source": "The New York Times", "word_count": "174", "document_type": "article", "news_desk": "Letters", "headline": {"kicker": "Letter", "content_kicker": "Letter", "main": "A \u2018Caregiving Credit\u2019 for Social Security Benefits", "print_headline": "A \u2018Caregiving Credit\u2019"}}