{"lead_paragraph": "New I.O.C. guidelines say transgender athletes should be allowed to take part in international events without undergoing sex reassignment surgery.", "pub_date": "2016-01-26T00:00:00Z", "slideshow_credits": null, "byline": {"organization": "THE ASSOCIATED PRESS", "person": [], "original": "By THE ASSOCIATED PRESS"}, "document_type": "article", "section_name": "Sports", "snippet": "New I.O.C. guidelines say transgender athletes should be allowed to take part in international events without undergoing sex reassignment surgery.", "multimedia": [], "blog": [], "type_of_material": "News", "headline": {"main": "Transgender Athletes Can Now Compete in Olympics Without Surgery"}, "keywords": [{"rank": "1", "name": "subject", "is_major": "N", "value": "Athletics and Sports"}, {"rank": "2", "name": "subject", "is_major": "N", "value": "Olympic Games (2016)"}, {"rank": "3", "name": "organizations", "is_major": "N", "value": "International Olympic Committee"}, {"rank": "4", "name": "subject", "is_major": "N", "value": "Transgender and Transsexuals"}], "web_url": "http://www.nytimes.com/2016/01/26/sports/olympics/transgender-athletes-olympics-ioc.html", "print_page": null, "source": "The New York Times", "news_desk": "Sports", "abstract": null, "word_count": "855", "_id": "56a679c938f0d82e672488cb", "subsection_name": "Olympics"}